jasperstarter/__init__.py
jasperstarter/exeptions.py
pyjasperstarter-0.0.1.dist-info/METADATA
pyjasperstarter-0.0.1.dist-info/WHEEL
pyjasperstarter-0.0.1.dist-info/top_level.txt
pyjasperstarter-0.0.1.dist-info/RECORD
